mysoc_validator/__init__.py
mysoc_validator/__main__.py
mysoc_validator/generate_model_descriptions.py
mysoc_validator/models/consts.py
mysoc_validator/models/dates.py
mysoc_validator/models/info.py
mysoc_validator/models/interests.py
mysoc_validator/models/popolo.py
mysoc_validator/models/transcripts.py
mysoc_validator/models/xml_base/__init__.py
mysoc_validator/models/xml_base/xml_base.py
mysoc_validator/models/xml_base/xml_to_json.py
mysoc_validator/models/xml_interests.py
mysoc_validator/py.typed
mysoc_validator/utils/parlparse/downloader.py
mysoc_validator/utils/parlparse/enum_helpers.py
mysoc_validator-1.2.0.dist-info/METADATA
mysoc_validator-1.2.0.dist-info/WHEEL
mysoc_validator-1.2.0.dist-info/entry_points.txt
mysoc_validator-1.2.0.dist-info/licenses/LICENSE.md
mysoc_validator-1.2.0.dist-info/RECORD
