Metadata-Version: 2.4
Name: mysoc-validator
Version: 1.2.0
Summary: Pydantic validators for mySociety democracy types
License: MIT
License-File: LICENSE.md
Author: mySociety
Author-email: alex.parsons@mysociety.org
Requires-Python: >=3.9,<4.0
Classifier: License :: OSI Approved :: MIT License
Classifier: Programming Language :: Python :: 3
Classifier: Programming Language :: Python :: 3.9
Classifier: Programming Language :: Python :: 3.10
Classifier: Programming Language :: Python :: 3.11
Classifier: Programming Language :: Python :: 3.12
Classifier: Programming Language :: Python :: 3.13
Classifier: Programming Language :: Python :: 3.14
Requires-Dist: click (>=8.1.0,<9.0.0)
Requires-Dist: httpx (>=0.27.2,<1.0.0)
Requires-Dist: lxml (>=4.0.0,<6.0.0)
Requires-Dist: nest-asyncio (>=1.6.0,<2.0.0)
Requires-Dist: pydantic (>=2.7.1,<3.0.0)
Requires-Dist: requests (>=2.32.3,<3.0.0)
Requires-Dist: rich (>=10.0.0,<14.0.0)
Requires-Dist: tqdm (>=4.67.1,<5.0.0)
Requires-Dist: trogon (>=0.6.0,<0.7.0)
Requires-Dist: typer (>=0.12.3,<0.13.0)
Requires-Dist: typing-extensions (>=4.11.0,<5.0.0)
Project-URL: Homepage, https://github.com/mysociety/mysoc-validator
Project-URL: Repository, https://github.com/mysociety/mysoc-validator
